{
  "version": "5",
  "dialect": "sqlite",
  "id": "f01d6037-ec4c-4945-9030-e44dcdc8e6eb",
  "prevId": "00000000-0000-0000-0000-000000000000",
  "tables": {
    "applications": {
      "name": "applications",
      "columns": {
        "id": {
          "name": "id",
          "type": "text(255)",
          "primaryKey": true,
          "notNull": true,
          "autoincrement": false
        },
        "tenant_id": {
          "name": "tenant_id",
          "type": "text(255)",
          "primaryKey": false,
          "notNull": true,
          "autoincrement": false
        },
        "name": {
          "name": "name",
          "type": "text(255)",
          "primaryKey": false,
          "notNull": true,
          "autoincrement": false
        },
        "client_secret": {
          "name": "client_secret",
          "type": "text(255)",
          "primaryKey": false,
          "notNull": false,
          "autoincrement": false
        },
        "allowed_callback_urls": {
          "name": "allowed_callback_urls",
          "type": "text(255)",
          "primaryKey": false,
          "notNull": false,
          "autoincrement": false
        },
        "allowed_logout_urls": {
          "name": "allowed_logout_urls",
          "type": "text(255)",
          "primaryKey": false,
          "notNull": false,
          "autoincrement": false
        },
        "allowed_web_origins": {
          "name": "allowed_web_origins",
          "type": "text(255)",
          "primaryKey": false,
          "notNull": false,
          "autoincrement": false
        },
        "authentication_settings": {
          "name": "authentication_settings",
          "type": "text(255)",
          "primaryKey": false,
          "notNull": false,
          "autoincrement": false
        },
        "styling_settings": {
          "name": "styling_settings",
          "type": "text(255)",
          "primaryKey": false,
          "notNull": false,
          "autoincrement": false
        },
        "email_validation": {
          "name": "email_validation",
          "type": "text(255)",
          "primaryKey": false,
          "notNull": false,
          "autoincrement": false
        },
        "created_at": {
          "name": "created_at",
          "type": "text(255)",
          "primaryKey": false,
          "notNull": false,
          "autoincrement": false
        },
        "updated_at": {
          "name": "updated_at",
          "type": "text(255)",
          "primaryKey": false,
          "notNull": false,
          "autoincrement": false
        }
      },
      "indexes": {},
      "foreignKeys": {},
      "compositePrimaryKeys": {},
      "uniqueConstraints": {}
    },
    "codes": {
      "name": "codes",
      "columns": {
        "id": {
          "name": "id",
          "type": "text(255)",
          "primaryKey": true,
          "notNull": true,
          "autoincrement": false
        },
        "tenant_id": {
          "name": "tenant_id",
          "type": "text(255)",
          "primaryKey": false,
          "notNull": true,
          "autoincrement": false
        },
        "user_id": {
          "name": "user_id",
          "type": "text(255)",
          "primaryKey": false,
          "notNull": true,
          "autoincrement": false
        },
        "type": {
          "name": "type",
          "type": "text(255)",
          "primaryKey": false,
          "notNull": true,
          "autoincrement": false
        },
        "created_at": {
          "name": "created_at",
          "type": "text(255)",
          "primaryKey": false,
          "notNull": true,
          "autoincrement": false
        },
        "expires_at": {
          "name": "expires_at",
          "type": "text(255)",
          "primaryKey": false,
          "notNull": true,
          "autoincrement": false
        },
        "used_at": {
          "name": "used_at",
          "type": "text(255)",
          "primaryKey": false,
          "notNull": false,
          "autoincrement": false
        },
        "code": {
          "name": "code",
          "type": "text(255)",
          "primaryKey": false,
          "notNull": true,
          "autoincrement": false
        }
      },
      "indexes": {
        "codes_expires_at_index": {
          "name": "codes_expires_at_index",
          "columns": ["expires_at"],
          "isUnique": false
        }
      },
      "foreignKeys": {},
      "compositePrimaryKeys": {},
      "uniqueConstraints": {}
    },
    "connections": {
      "name": "connections",
      "columns": {
        "id": {
          "name": "id",
          "type": "text(255)",
          "primaryKey": true,
          "notNull": true,
          "autoincrement": false
        },
        "tenant_id": {
          "name": "tenant_id",
          "type": "text(255)",
          "primaryKey": false,
          "notNull": true,
          "autoincrement": false
        },
        "name": {
          "name": "name",
          "type": "text(255)",
          "primaryKey": false,
          "notNull": true,
          "autoincrement": false
        },
        "client_id": {
          "name": "client_id",
          "type": "text(255)",
          "primaryKey": false,
          "notNull": false,
          "autoincrement": false
        },
        "client_secret": {
          "name": "client_secret",
          "type": "text(255)",
          "primaryKey": false,
          "notNull": false,
          "autoincrement": false
        },
        "authorization_endpoint": {
          "name": "authorization_endpoint",
          "type": "text(255)",
          "primaryKey": false,
          "notNull": false,
          "autoincrement": false
        },
        "token_endpoint": {
          "name": "token_endpoint",
          "type": "text(255)",
          "primaryKey": false,
          "notNull": false,
          "autoincrement": false
        },
        "scope": {
          "name": "scope",
          "type": "text(255)",
          "primaryKey": false,
          "notNull": false,
          "autoincrement": false
        },
        "response_type": {
          "name": "response_type",
          "type": "text(255)",
          "primaryKey": false,
          "notNull": false,
          "autoincrement": false
        },
        "response_mode": {
          "name": "response_mode",
          "type": "text(255)",
          "primaryKey": false,
          "notNull": false,
          "autoincrement": false
        },
        "private_key": {
          "name": "private_key",
          "type": "text(767)",
          "primaryKey": false,
          "notNull": false,
          "autoincrement": false
        },
        "kid": {
          "name": "kid",
          "type": "text(255)",
          "primaryKey": false,
          "notNull": false,
          "autoincrement": false
        },
        "team_id": {
          "name": "team_id",
          "type": "text(255)",
          "primaryKey": false,
          "notNull": false,
          "autoincrement": false
        },
        "created_at": {
          "name": "created_at",
          "type": "text(255)",
          "primaryKey": false,
          "notNull": false,
          "autoincrement": false
        },
        "updated_at": {
          "name": "updated_at",
          "type": "text(255)",
          "primaryKey": false,
          "notNull": false,
          "autoincrement": false
        },
        "userinfo_endpoint": {
          "name": "userinfo_endpoint",
          "type": "text(256)",
          "primaryKey": false,
          "notNull": false,
          "autoincrement": false
        }
      },
      "indexes": {},
      "foreignKeys": {},
      "compositePrimaryKeys": {},
      "uniqueConstraints": {}
    },
    "domains": {
      "name": "domains",
      "columns": {
        "id": {
          "name": "id",
          "type": "text(255)",
          "primaryKey": true,
          "notNull": true,
          "autoincrement": false
        },
        "tenant_id": {
          "name": "tenant_id",
          "type": "text(255)",
          "primaryKey": false,
          "notNull": true,
          "autoincrement": false
        },
        "domain": {
          "name": "domain",
          "type": "text(255)",
          "primaryKey": false,
          "notNull": true,
          "autoincrement": false
        },
        "email_service": {
          "name": "email_service",
          "type": "text(255)",
          "primaryKey": false,
          "notNull": false,
          "autoincrement": false
        },
        "email_api_key": {
          "name": "email_api_key",
          "type": "text(255)",
          "primaryKey": false,
          "notNull": false,
          "autoincrement": false
        },
        "dkim_private_key": {
          "name": "dkim_private_key",
          "type": "text(2048)",
          "primaryKey": false,
          "notNull": false,
          "autoincrement": false
        },
        "dkim_public_key": {
          "name": "dkim_public_key",
          "type": "text(2048)",
          "primaryKey": false,
          "notNull": false,
          "autoincrement": false
        },
        "created_at": {
          "name": "created_at",
          "type": "text(255)",
          "primaryKey": false,
          "notNull": false,
          "autoincrement": false
        },
        "updated_at": {
          "name": "updated_at",
          "type": "text(255)",
          "primaryKey": false,
          "notNull": false,
          "autoincrement": false
        }
      },
      "indexes": {},
      "foreignKeys": {},
      "compositePrimaryKeys": {},
      "uniqueConstraints": {}
    },
    "keys": {
      "name": "keys",
      "columns": {
        "kid": {
          "name": "kid",
          "type": "text(255)",
          "primaryKey": true,
          "notNull": true,
          "autoincrement": false
        },
        "tenant_id": {
          "name": "tenant_id",
          "type": "text(255)",
          "primaryKey": false,
          "notNull": false,
          "autoincrement": false
        },
        "private_key": {
          "name": "private_key",
          "type": "text(8192)",
          "primaryKey": false,
          "notNull": false,
          "autoincrement": false
        },
        "public_key": {
          "name": "public_key",
          "type": "text(1024)",
          "primaryKey": false,
          "notNull": false,
          "autoincrement": false
        },
        "created_at": {
          "name": "created_at",
          "type": "text(255)",
          "primaryKey": false,
          "notNull": false,
          "autoincrement": false
        },
        "revoked_at": {
          "name": "revoked_at",
          "type": "text(255)",
          "primaryKey": false,
          "notNull": false,
          "autoincrement": false
        }
      },
      "indexes": {},
      "foreignKeys": {},
      "compositePrimaryKeys": {},
      "uniqueConstraints": {}
    },
    "logs": {
      "name": "logs",
      "columns": {
        "id": {
          "name": "id",
          "type": "text(255)",
          "primaryKey": true,
          "notNull": true,
          "autoincrement": false
        },
        "tenant_id": {
          "name": "tenant_id",
          "type": "text(255)",
          "primaryKey": false,
          "notNull": true,
          "autoincrement": false
        },
        "user_id": {
          "name": "user_id",
          "type": "text(255)",
          "primaryKey": false,
          "notNull": true,
          "autoincrement": false
        },
        "ip": {
          "name": "ip",
          "type": "text(255)",
          "primaryKey": false,
          "notNull": false,
          "autoincrement": false
        },
        "type": {
          "name": "type",
          "type": "text(255)",
          "primaryKey": false,
          "notNull": false,
          "autoincrement": false
        },
        "date": {
          "name": "date",
          "type": "text(255)",
          "primaryKey": false,
          "notNull": false,
          "autoincrement": false
        },
        "description": {
          "name": "description",
          "type": "text(255)",
          "primaryKey": false,
          "notNull": false,
          "autoincrement": false
        },
        "client_id": {
          "name": "client_id",
          "type": "text(255)",
          "primaryKey": false,
          "notNull": false,
          "autoincrement": false
        },
        "client_name": {
          "name": "client_name",
          "type": "text(255)",
          "primaryKey": false,
          "notNull": false,
          "autoincrement": false
        },
        "user_agent": {
          "name": "user_agent",
          "type": "text(255)",
          "primaryKey": false,
          "notNull": false,
          "autoincrement": false
        },
        "details": {
          "name": "details",
          "type": "text(8192)",
          "primaryKey": false,
          "notNull": false,
          "autoincrement": false
        },
        "user_name": {
          "name": "user_name",
          "type": "text(255)",
          "primaryKey": false,
          "notNull": false,
          "autoincrement": false
        },
        "auth0_client": {
          "name": "auth0_client",
          "type": "text(255)",
          "primaryKey": false,
          "notNull": false,
          "autoincrement": false
        },
        "isMobile": {
          "name": "isMobile",
          "type": "integer",
          "primaryKey": false,
          "notNull": false,
          "autoincrement": false
        },
        "connection": {
          "name": "connection",
          "type": "text(255)",
          "primaryKey": false,
          "notNull": false,
          "autoincrement": false
        },
        "connection_id": {
          "name": "connection_id",
          "type": "text(255)",
          "primaryKey": false,
          "notNull": false,
          "autoincrement": false
        },
        "audience": {
          "name": "audience",
          "type": "text(255)",
          "primaryKey": false,
          "notNull": false,
          "autoincrement": false
        },
        "scope": {
          "name": "scope",
          "type": "text(255)",
          "primaryKey": false,
          "notNull": false,
          "autoincrement": false
        },
        "strategy": {
          "name": "strategy",
          "type": "text(255)",
          "primaryKey": false,
          "notNull": false,
          "autoincrement": false
        },
        "strategy_type": {
          "name": "strategy_type",
          "type": "text(255)",
          "primaryKey": false,
          "notNull": false,
          "autoincrement": false
        },
        "hostname": {
          "name": "hostname",
          "type": "text(255)",
          "primaryKey": false,
          "notNull": false,
          "autoincrement": false
        },
        "session_connection": {
          "name": "session_connection",
          "type": "text(255)",
          "primaryKey": false,
          "notNull": false,
          "autoincrement": false
        }
      },
      "indexes": {
        "logs_user_id_index": {
          "name": "logs_user_id_index",
          "columns": ["user_id"],
          "isUnique": false
        },
        "logs_tenant_id_index": {
          "name": "logs_tenant_id_index",
          "columns": ["tenant_id"],
          "isUnique": false
        },
        "logs_date_index": {
          "name": "logs_date_index",
          "columns": ["date"],
          "isUnique": false
        }
      },
      "foreignKeys": {
        "logs_tenant_id_tenants_id_fk": {
          "name": "logs_tenant_id_tenants_id_fk",
          "tableFrom": "logs",
          "tableTo": "tenants",
          "columnsFrom": ["tenant_id"],
          "columnsTo": ["id"],
          "onDelete": "cascade",
          "onUpdate": "no action"
        }
      },
      "compositePrimaryKeys": {},
      "uniqueConstraints": {}
    },
    "members": {
      "name": "members",
      "columns": {
        "id": {
          "name": "id",
          "type": "text(255)",
          "primaryKey": true,
          "notNull": true,
          "autoincrement": false
        },
        "tenant_id": {
          "name": "tenant_id",
          "type": "text(255)",
          "primaryKey": false,
          "notNull": true,
          "autoincrement": false
        },
        "sub": {
          "name": "sub",
          "type": "text(255)",
          "primaryKey": false,
          "notNull": false,
          "autoincrement": false
        },
        "email": {
          "name": "email",
          "type": "text(255)",
          "primaryKey": false,
          "notNull": false,
          "autoincrement": false
        },
        "name": {
          "name": "name",
          "type": "text(255)",
          "primaryKey": false,
          "notNull": false,
          "autoincrement": false
        },
        "status": {
          "name": "status",
          "type": "text(255)",
          "primaryKey": false,
          "notNull": false,
          "autoincrement": false
        },
        "role": {
          "name": "role",
          "type": "text(255)",
          "primaryKey": false,
          "notNull": false,
          "autoincrement": false
        },
        "picture": {
          "name": "picture",
          "type": "text(255)",
          "primaryKey": false,
          "notNull": false,
          "autoincrement": false
        },
        "created_at": {
          "name": "created_at",
          "type": "text(255)",
          "primaryKey": false,
          "notNull": false,
          "autoincrement": false
        },
        "updated_at": {
          "name": "updated_at",
          "type": "text(255)",
          "primaryKey": false,
          "notNull": false,
          "autoincrement": false
        }
      },
      "indexes": {},
      "foreignKeys": {
        "members_tenant_id_tenants_id_fk": {
          "name": "members_tenant_id_tenants_id_fk",
          "tableFrom": "members",
          "tableTo": "tenants",
          "columnsFrom": ["tenant_id"],
          "columnsTo": ["id"],
          "onDelete": "cascade",
          "onUpdate": "no action"
        }
      },
      "compositePrimaryKeys": {},
      "uniqueConstraints": {}
    },
    "migrations": {
      "name": "migrations",
      "columns": {
        "id": {
          "name": "id",
          "type": "text(255)",
          "primaryKey": true,
          "notNull": true,
          "autoincrement": false
        },
        "tenant_id": {
          "name": "tenant_id",
          "type": "text(255)",
          "primaryKey": false,
          "notNull": true,
          "autoincrement": false
        },
        "provider": {
          "name": "provider",
          "type": "text(255)",
          "primaryKey": false,
          "notNull": false,
          "autoincrement": false
        },
        "client_id": {
          "name": "client_id",
          "type": "text(255)",
          "primaryKey": false,
          "notNull": false,
          "autoincrement": false
        },
        "origin": {
          "name": "origin",
          "type": "text(255)",
          "primaryKey": false,
          "notNull": false,
          "autoincrement": false
        },
        "domain": {
          "name": "domain",
          "type": "text(255)",
          "primaryKey": false,
          "notNull": false,
          "autoincrement": false
        },
        "created_at": {
          "name": "created_at",
          "type": "text(255)",
          "primaryKey": false,
          "notNull": false,
          "autoincrement": false
        },
        "updated_at": {
          "name": "updated_at",
          "type": "text(255)",
          "primaryKey": false,
          "notNull": false,
          "autoincrement": false
        }
      },
      "indexes": {},
      "foreignKeys": {
        "migrations_tenant_id_tenants_id_fk": {
          "name": "migrations_tenant_id_tenants_id_fk",
          "tableFrom": "migrations",
          "tableTo": "tenants",
          "columnsFrom": ["tenant_id"],
          "columnsTo": ["id"],
          "onDelete": "cascade",
          "onUpdate": "no action"
        }
      },
      "compositePrimaryKeys": {},
      "uniqueConstraints": {}
    },
    "otps": {
      "name": "otps",
      "columns": {
        "tenant_id": {
          "name": "tenant_id",
          "type": "text(255)",
          "primaryKey": false,
          "notNull": true,
          "autoincrement": false
        },
        "id": {
          "name": "id",
          "type": "text(255)",
          "primaryKey": true,
          "notNull": true,
          "autoincrement": false
        },
        "client_id": {
          "name": "client_id",
          "type": "text(255)",
          "primaryKey": false,
          "notNull": true,
          "autoincrement": false
        },
        "code": {
          "name": "code",
          "type": "text(255)",
          "primaryKey": false,
          "notNull": true,
          "autoincrement": false
        },
        "email": {
          "name": "email",
          "type": "text(255)",
          "primaryKey": false,
          "notNull": true,
          "autoincrement": false
        },
        "user_id": {
          "name": "user_id",
          "type": "text(255)",
          "primaryKey": false,
          "notNull": false,
          "autoincrement": false
        },
        "send": {
          "name": "send",
          "type": "text(255)",
          "primaryKey": false,
          "notNull": false,
          "autoincrement": false
        },
        "nonce": {
          "name": "nonce",
          "type": "text(255)",
          "primaryKey": false,
          "notNull": false,
          "autoincrement": false
        },
        "state": {
          "name": "state",
          "type": "text(1024)",
          "primaryKey": false,
          "notNull": false,
          "autoincrement": false
        },
        "scope": {
          "name": "scope",
          "type": "text(1024)",
          "primaryKey": false,
          "notNull": false,
          "autoincrement": false
        },
        "response_type": {
          "name": "response_type",
          "type": "text(256)",
          "primaryKey": false,
          "notNull": false,
          "autoincrement": false
        },
        "response_mode": {
          "name": "response_mode",
          "type": "text(256)",
          "primaryKey": false,
          "notNull": false,
          "autoincrement": false
        },
        "redirect_uri": {
          "name": "redirect_uri",
          "type": "text(1024)",
          "primaryKey": false,
          "notNull": false,
          "autoincrement": false
        },
        "created_at": {
          "name": "created_at",
          "type": "text(255)",
          "primaryKey": false,
          "notNull": true,
          "autoincrement": false
        },
        "expires_at": {
          "name": "expires_at",
          "type": "text(255)",
          "primaryKey": false,
          "notNull": true,
          "autoincrement": false
        },
        "used_at": {
          "name": "used_at",
          "type": "text(255)",
          "primaryKey": false,
          "notNull": false,
          "autoincrement": false
        },
        "audience": {
          "name": "audience",
          "type": "text(255)",
          "primaryKey": false,
          "notNull": false,
          "autoincrement": false
        }
      },
      "indexes": {
        "otps_email_index": {
          "name": "otps_email_index",
          "columns": ["email"],
          "isUnique": false
        },
        "otps_expires_at_index": {
          "name": "otps_expires_at_index",
          "columns": ["expires_at"],
          "isUnique": false
        }
      },
      "foreignKeys": {
        "otps_tenant_id_tenants_id_fk": {
          "name": "otps_tenant_id_tenants_id_fk",
          "tableFrom": "otps",
          "tableTo": "tenants",
          "columnsFrom": ["tenant_id"],
          "columnsTo": ["id"],
          "onDelete": "cascade",
          "onUpdate": "no action"
        }
      },
      "compositePrimaryKeys": {},
      "uniqueConstraints": {}
    },
    "passwords": {
      "name": "passwords",
      "columns": {
        "tenant_id": {
          "name": "tenant_id",
          "type": "text(255)",
          "primaryKey": false,
          "notNull": true,
          "autoincrement": false
        },
        "user_id": {
          "name": "user_id",
          "type": "text(255)",
          "primaryKey": true,
          "notNull": true,
          "autoincrement": false
        },
        "created_at": {
          "name": "created_at",
          "type": "text(255)",
          "primaryKey": false,
          "notNull": false,
          "autoincrement": false
        },
        "updated_at": {
          "name": "updated_at",
          "type": "text(255)",
          "primaryKey": false,
          "notNull": false,
          "autoincrement": false
        },
        "password": {
          "name": "password",
          "type": "text(255)",
          "primaryKey": false,
          "notNull": true,
          "autoincrement": false
        }
      },
      "indexes": {},
      "foreignKeys": {
        "passwords_tenant_id_tenants_id_fk": {
          "name": "passwords_tenant_id_tenants_id_fk",
          "tableFrom": "passwords",
          "tableTo": "tenants",
          "columnsFrom": ["tenant_id"],
          "columnsTo": ["id"],
          "onDelete": "cascade",
          "onUpdate": "no action"
        }
      },
      "compositePrimaryKeys": {},
      "uniqueConstraints": {}
    },
    "sessions": {
      "name": "sessions",
      "columns": {
        "tenant_id": {
          "name": "tenant_id",
          "type": "text(255)",
          "primaryKey": false,
          "notNull": true,
          "autoincrement": false
        },
        "id": {
          "name": "id",
          "type": "text(255)",
          "primaryKey": true,
          "notNull": true,
          "autoincrement": false
        },
        "client_id": {
          "name": "client_id",
          "type": "text(255)",
          "primaryKey": false,
          "notNull": true,
          "autoincrement": false
        },
        "user_id": {
          "name": "user_id",
          "type": "text(255)",
          "primaryKey": false,
          "notNull": true,
          "autoincrement": false
        },
        "created_at": {
          "name": "created_at",
          "type": "text(255)",
          "primaryKey": false,
          "notNull": false,
          "autoincrement": false
        },
        "expires_at": {
          "name": "expires_at",
          "type": "text(255)",
          "primaryKey": false,
          "notNull": false,
          "autoincrement": false
        },
        "used_at": {
          "name": "used_at",
          "type": "text(255)",
          "primaryKey": false,
          "notNull": false,
          "autoincrement": false
        },
        "deleted_at": {
          "name": "deleted_at",
          "type": "text(255)",
          "primaryKey": false,
          "notNull": false,
          "autoincrement": false
        }
      },
      "indexes": {},
      "foreignKeys": {
        "sessions_tenant_id_tenants_id_fk": {
          "name": "sessions_tenant_id_tenants_id_fk",
          "tableFrom": "sessions",
          "tableTo": "tenants",
          "columnsFrom": ["tenant_id"],
          "columnsTo": ["id"],
          "onDelete": "cascade",
          "onUpdate": "no action"
        }
      },
      "compositePrimaryKeys": {},
      "uniqueConstraints": {}
    },
    "tenants": {
      "name": "tenants",
      "columns": {
        "id": {
          "name": "id",
          "type": "text(255)",
          "primaryKey": true,
          "notNull": true,
          "autoincrement": false
        },
        "name": {
          "name": "name",
          "type": "text(255)",
          "primaryKey": false,
          "notNull": false,
          "autoincrement": false
        },
        "audience": {
          "name": "audience",
          "type": "text(255)",
          "primaryKey": false,
          "notNull": false,
          "autoincrement": false
        },
        "sender_email": {
          "name": "sender_email",
          "type": "text(255)",
          "primaryKey": false,
          "notNull": false,
          "autoincrement": false
        },
        "sender_name": {
          "name": "sender_name",
          "type": "text(255)",
          "primaryKey": false,
          "notNull": false,
          "autoincrement": false
        },
        "language": {
          "name": "language",
          "type": "text(255)",
          "primaryKey": false,
          "notNull": false,
          "autoincrement": false
        },
        "logo": {
          "name": "logo",
          "type": "text(255)",
          "primaryKey": false,
          "notNull": false,
          "autoincrement": false
        },
        "primary_color": {
          "name": "primary_color",
          "type": "text(255)",
          "primaryKey": false,
          "notNull": false,
          "autoincrement": false
        },
        "secondary_color": {
          "name": "secondary_color",
          "type": "text(255)",
          "primaryKey": false,
          "notNull": false,
          "autoincrement": false
        },
        "created_at": {
          "name": "created_at",
          "type": "text(255)",
          "primaryKey": false,
          "notNull": false,
          "autoincrement": false
        },
        "updated_at": {
          "name": "updated_at",
          "type": "text(255)",
          "primaryKey": false,
          "notNull": false,
          "autoincrement": false
        },
        "support_url": {
          "name": "support_url",
          "type": "text(255)",
          "primaryKey": false,
          "notNull": false,
          "autoincrement": false
        }
      },
      "indexes": {},
      "foreignKeys": {},
      "compositePrimaryKeys": {},
      "uniqueConstraints": {}
    },
    "tickets": {
      "name": "tickets",
      "columns": {
        "tenant_id": {
          "name": "tenant_id",
          "type": "text(255)",
          "primaryKey": false,
          "notNull": true,
          "autoincrement": false
        },
        "id": {
          "name": "id",
          "type": "text(255)",
          "primaryKey": true,
          "notNull": true,
          "autoincrement": false
        },
        "client_id": {
          "name": "client_id",
          "type": "text(255)",
          "primaryKey": false,
          "notNull": true,
          "autoincrement": false
        },
        "email": {
          "name": "email",
          "type": "text(255)",
          "primaryKey": false,
          "notNull": true,
          "autoincrement": false
        },
        "nonce": {
          "name": "nonce",
          "type": "text(255)",
          "primaryKey": false,
          "notNull": false,
          "autoincrement": false
        },
        "state": {
          "name": "state",
          "type": "text(1024)",
          "primaryKey": false,
          "notNull": false,
          "autoincrement": false
        },
        "scope": {
          "name": "scope",
          "type": "text(1024)",
          "primaryKey": false,
          "notNull": false,
          "autoincrement": false
        },
        "response_type": {
          "name": "response_type",
          "type": "text(256)",
          "primaryKey": false,
          "notNull": false,
          "autoincrement": false
        },
        "response_mode": {
          "name": "response_mode",
          "type": "text(256)",
          "primaryKey": false,
          "notNull": false,
          "autoincrement": false
        },
        "redirect_uri": {
          "name": "redirect_uri",
          "type": "text(1024)",
          "primaryKey": false,
          "notNull": false,
          "autoincrement": false
        },
        "created_at": {
          "name": "created_at",
          "type": "text(255)",
          "primaryKey": false,
          "notNull": true,
          "autoincrement": false
        },
        "expires_at": {
          "name": "expires_at",
          "type": "text(255)",
          "primaryKey": false,
          "notNull": true,
          "autoincrement": false
        },
        "used_at": {
          "name": "used_at",
          "type": "text(255)",
          "primaryKey": false,
          "notNull": false,
          "autoincrement": false
        }
      },
      "indexes": {},
      "foreignKeys": {
        "tickets_tenant_id_tenants_id_fk": {
          "name": "tickets_tenant_id_tenants_id_fk",
          "tableFrom": "tickets",
          "tableTo": "tenants",
          "columnsFrom": ["tenant_id"],
          "columnsTo": ["id"],
          "onDelete": "cascade",
          "onUpdate": "no action"
        }
      },
      "compositePrimaryKeys": {},
      "uniqueConstraints": {}
    },
    "universal_login_sessions": {
      "name": "universal_login_sessions",
      "columns": {
        "id": {
          "name": "id",
          "type": "text(255)",
          "primaryKey": true,
          "notNull": true,
          "autoincrement": false
        },
        "tenant_id": {
          "name": "tenant_id",
          "type": "text(255)",
          "primaryKey": false,
          "notNull": true,
          "autoincrement": false
        },
        "client_id": {
          "name": "client_id",
          "type": "text(255)",
          "primaryKey": false,
          "notNull": true,
          "autoincrement": false
        },
        "username": {
          "name": "username",
          "type": "text(255)",
          "primaryKey": false,
          "notNull": false,
          "autoincrement": false
        },
        "response_type": {
          "name": "response_type",
          "type": "text(255)",
          "primaryKey": false,
          "notNull": false,
          "autoincrement": false
        },
        "response_mode": {
          "name": "response_mode",
          "type": "text(255)",
          "primaryKey": false,
          "notNull": false,
          "autoincrement": false
        },
        "audience": {
          "name": "audience",
          "type": "text(255)",
          "primaryKey": false,
          "notNull": false,
          "autoincrement": false
        },
        "scope": {
          "name": "scope",
          "type": "text(511)",
          "primaryKey": false,
          "notNull": false,
          "autoincrement": false
        },
        "state": {
          "name": "state",
          "type": "text(511)",
          "primaryKey": false,
          "notNull": false,
          "autoincrement": false
        },
        "code_challenge_method": {
          "name": "code_challenge_method",
          "type": "text(256)",
          "primaryKey": false,
          "notNull": false,
          "autoincrement": false
        },
        "code_challenge": {
          "name": "code_challenge",
          "type": "text(256)",
          "primaryKey": false,
          "notNull": false,
          "autoincrement": false
        },
        "redirect_uri": {
          "name": "redirect_uri",
          "type": "text(256)",
          "primaryKey": false,
          "notNull": false,
          "autoincrement": false
        },
        "created_at": {
          "name": "created_at",
          "type": "text(255)",
          "primaryKey": false,
          "notNull": true,
          "autoincrement": false
        },
        "updated_at": {
          "name": "updated_at",
          "type": "text(255)",
          "primaryKey": false,
          "notNull": true,
          "autoincrement": false
        },
        "expires_at": {
          "name": "expires_at",
          "type": "text(255)",
          "primaryKey": false,
          "notNull": true,
          "autoincrement": false
        },
        "nonce": {
          "name": "nonce",
          "type": "text(255)",
          "primaryKey": false,
          "notNull": false,
          "autoincrement": false
        }
      },
      "indexes": {},
      "foreignKeys": {
        "universal_login_sessions_tenant_id_tenants_id_fk": {
          "name": "universal_login_sessions_tenant_id_tenants_id_fk",
          "tableFrom": "universal_login_sessions",
          "tableTo": "tenants",
          "columnsFrom": ["tenant_id"],
          "columnsTo": ["id"],
          "onDelete": "cascade",
          "onUpdate": "no action"
        }
      },
      "compositePrimaryKeys": {},
      "uniqueConstraints": {}
    },
    "users": {
      "name": "users",
      "columns": {
        "id": {
          "name": "id",
          "type": "text(255)",
          "primaryKey": false,
          "notNull": true,
          "autoincrement": false
        },
        "tenant_id": {
          "name": "tenant_id",
          "type": "text(255)",
          "primaryKey": false,
          "notNull": true,
          "autoincrement": false
        },
        "email": {
          "name": "email",
          "type": "text(255)",
          "primaryKey": false,
          "notNull": true,
          "autoincrement": false
        },
        "given_name": {
          "name": "given_name",
          "type": "text(255)",
          "primaryKey": false,
          "notNull": false,
          "autoincrement": false
        },
        "family_name": {
          "name": "family_name",
          "type": "text(255)",
          "primaryKey": false,
          "notNull": false,
          "autoincrement": false
        },
        "nickname": {
          "name": "nickname",
          "type": "text(255)",
          "primaryKey": false,
          "notNull": false,
          "autoincrement": false
        },
        "name": {
          "name": "name",
          "type": "text(255)",
          "primaryKey": false,
          "notNull": false,
          "autoincrement": false
        },
        "picture": {
          "name": "picture",
          "type": "text(2083)",
          "primaryKey": false,
          "notNull": false,
          "autoincrement": false
        },
        "created_at": {
          "name": "created_at",
          "type": "text(255)",
          "primaryKey": false,
          "notNull": false,
          "autoincrement": false
        },
        "updated_at": {
          "name": "updated_at",
          "type": "text(255)",
          "primaryKey": false,
          "notNull": false,
          "autoincrement": false
        },
        "linked_to": {
          "name": "linked_to",
          "type": "text(255)",
          "primaryKey": false,
          "notNull": false,
          "autoincrement": false
        },
        "last_ip": {
          "name": "last_ip",
          "type": "text(255)",
          "primaryKey": false,
          "notNull": false,
          "autoincrement": false
        },
        "login_count": {
          "name": "login_count",
          "type": "integer",
          "primaryKey": false,
          "notNull": false,
          "autoincrement": false
        },
        "last_login": {
          "name": "last_login",
          "type": "text(255)",
          "primaryKey": false,
          "notNull": false,
          "autoincrement": false
        },
        "provider": {
          "name": "provider",
          "type": "text(255)",
          "primaryKey": false,
          "notNull": false,
          "autoincrement": false
        },
        "connection": {
          "name": "connection",
          "type": "text(255)",
          "primaryKey": false,
          "notNull": false,
          "autoincrement": false
        },
        "email_verified": {
          "name": "email_verified",
          "type": "integer",
          "primaryKey": false,
          "notNull": false,
          "autoincrement": false
        },
        "is_social": {
          "name": "is_social",
          "type": "integer",
          "primaryKey": false,
          "notNull": false,
          "autoincrement": false
        },
        "app_metadata": {
          "name": "app_metadata",
          "type": "text(8092)",
          "primaryKey": false,
          "notNull": false,
          "autoincrement": false
        },
        "profileData": {
          "name": "profileData",
          "type": "text(2048)",
          "primaryKey": false,
          "notNull": false,
          "autoincrement": false
        },
        "locale": {
          "name": "locale",
          "type": "text(255)",
          "primaryKey": false,
          "notNull": false,
          "autoincrement": false
        }
      },
      "indexes": {
        "users_email_index": {
          "name": "users_email_index",
          "columns": ["email"],
          "isUnique": false
        },
        "users_linked_to_index": {
          "name": "users_linked_to_index",
          "columns": ["linked_to"],
          "isUnique": false
        },
        "users_name_index": {
          "name": "users_name_index",
          "columns": ["name"],
          "isUnique": false
        },
        "unique_email_provider": {
          "name": "unique_email_provider",
          "columns": ["email", "provider", "tenant_id"],
          "isUnique": true
        }
      },
      "foreignKeys": {
        "users_tenant_id_tenants_id_fk": {
          "name": "users_tenant_id_tenants_id_fk",
          "tableFrom": "users",
          "tableTo": "tenants",
          "columnsFrom": ["tenant_id"],
          "columnsTo": ["id"],
          "onDelete": "cascade",
          "onUpdate": "no action"
        },
        "users_linked_to_tenant_id_users_id_tenant_id_fk": {
          "name": "users_linked_to_tenant_id_users_id_tenant_id_fk",
          "tableFrom": "users",
          "tableTo": "users",
          "columnsFrom": ["linked_to", "tenant_id"],
          "columnsTo": ["id", "tenant_id"],
          "onDelete": "cascade",
          "onUpdate": "no action"
        }
      },
      "compositePrimaryKeys": {
        "users_id_tenant_id": {
          "columns": ["id", "tenant_id"],
          "name": "users_id_tenant_id"
        }
      },
      "uniqueConstraints": {}
    }
  },
  "enums": {},
  "_meta": {
    "schemas": {},
    "tables": {},
    "columns": {}
  }
}
